googletrans/__init__.py
googletrans/client.py
googletrans/constants.py
googletrans/gtoken.py
googletrans/models.py
googletrans/urls.py
googletrans/utils.py
googletransfork-1.0.1.data/scripts/translate
googletransfork-1.0.1.dist-info/LICENSE
googletransfork-1.0.1.dist-info/METADATA
googletransfork-1.0.1.dist-info/WHEEL
googletransfork-1.0.1.dist-info/top_level.txt
googletransfork-1.0.1.dist-info/RECORD
