Metadata-Version: 2.1
Name: googletransfork
Version: 1.0.1
Summary: Free Google Translate API for Python. Translates totally free of charge.
Home-page: https://github.com/Suro4ek/py-googletrans
Author: SuHun Han, Suro
Author-email: ssut@ssut.me
License: MIT
Keywords: google translate translator
Classifier: Development Status :: 5 - Production/Stable
Classifier: Intended Audience :: Education
Classifier: Intended Audience :: End Users/Desktop
Classifier: License :: Freeware
Classifier: Operating System :: POSIX
Classifier: Operating System :: Microsoft :: Windows
Classifier: Operating System :: MacOS :: MacOS X
Classifier: Topic :: Education
Classifier: Programming Language :: Python
Classifier: Programming Language :: Python :: 3.6
Classifier: Programming Language :: Python :: 3.7
Classifier: Programming Language :: Python :: 3.8
Requires-Python: >=3.6
License-File: LICENSE
Requires-Dist: httpx ==0.13.3
